AutoTTS/__init__.py
AutoTTS/cli.py
AutoTTS/config.py
AutoTTS/core.py
AutoTTS/engines/__init__.py
AutoTTS/engines/azure.py
AutoTTS/engines/coqui.py
AutoTTS/engines/edge.py
AutoTTS/engines/elevenlabs.py
AutoTTS/engines/piper.py
AutoTTS/engines/pyttsx3.py
AutoTTS/engines/xtts.py
autotts-0.1.0.dist-info/METADATA
autotts-0.1.0.dist-info/WHEEL
autotts-0.1.0.dist-info/entry_points.txt
autotts-0.1.0.dist-info/top_level.txt
autotts-0.1.0.dist-info/RECORD
