Metadata-Version: 2.4
Name: AutoTTS
Version: 0.1.0
Summary: Multi-engine TTS wrapper with coconut protection
Author: PDGadm
Requires-Dist: edge-tts
Requires-Dist: pyttsx3
Requires-Dist: TTS
Requires-Dist: azure-cognitiveservices-speech
Requires-Dist: elevenlabs
Dynamic: author
Dynamic: requires-dist
Dynamic: summary
